gf_apps/__init__.py
gf_apps/gf_images/__init__.py
gf_apps/gf_images/gf_images_classify/__init__.py
gf_apps/gf_images/gf_images_classify/gf_images_classify.py
gf_apps/gf_images/gf_images_client/__init__.py
gf_apps/gf_images/gf_images_client/gf_images_client.py
gf_apps/gf_images/gf_images_core/__init__.py
gf_apps/gf_images/gf_images_core/gf_image.py
gf_apps/gf_images/gf_images_core/gf_image_db_mongo.py
gf_apps/gf_images/gf_images_core/gf_image_db_sql.py
gf_apps/gf_images/gf_images_core/gf_image_utils.py
gf_apps/gf_images/gf_images_core/gf_image_verify.py
gf_apps/gf_images/gf_images_palette/__init__.py
gf_apps/gf_images/gf_images_palette/gf_color_palette.py
gf_apps/gf_images/gf_images_palette/gf_color_palette_lib.py
gf_apps/gf_images/gf_images_palette/gf_test.py
gf_core/__init__.py
gf_core/gf_core_cli.py
gf_core/gf_core_db_mongo.py
gf_core/gf_core_db_sql.py
gf_core/gf_core_error.py
gf_core/gf_core_http.py
gf_core/gf_core_id.py
gf_core/gf_core_logger.py
gf_core/gf_core_utils.py
gf_extern_services/__init__.py
gf_extern_services/gf_aws/__init__.py
gf_extern_services/gf_aws/gf_aws_ec2.py
gf_extern_services/gf_aws/gf_aws_route53.py
gf_extern_services/gf_aws/gf_aws_s3.py
gf_extern_services/gf_aws/gf_aws_secrets.py
gf_extern_services/gf_aws/gf_os_aws_creds.py
gf_extern_services/gf_google/__init__.py
gf_extern_services/gf_google/gf_google_bigquery.py
gf_extern_services/gf_google/gf_google_sheets.py
gf_extern_services/gf_youtube/__init__.py
gf_extern_services/gf_youtube/gf_youtube.py
gf_identity/__init__.py
gf_identity/gf_identity.py
gf_ml/__init__.py
gf_ml/gf_llm_core.py
gf_ml/gf_ml_adapters/__init__.py
gf_ml/gf_ml_adapters/gf_google_ai.py
gf_observe/__init__.py
gf_observe/gf_extern_load.py
gf_observe/gf_extern_load_db.py
gf_ops/__init__.py
gf_ops/aws/__init__.py
gf_ops/aws/s3/__init__.py
gf_ops/aws/s3/gf_s3_data_info.py
gf_ops/containers/__init__.py
gf_ops/containers/gf_containers.py
gf_ops/containers/gf_os_docker.py
gf_ops/utils/__init__.py
gf_ops/utils/gf_build_changes.py
gloflow-0.1.41.dist-info/METADATA
gloflow-0.1.41.dist-info/WHEEL
gloflow-0.1.41.dist-info/top_level.txt
gloflow-0.1.41.dist-info/RECORD
